PiicoDev_BME280.py
PiicoDev_Buzzer.py
PiicoDev_CAP1203.py
PiicoDev_ENS160.py
PiicoDev_LIS3DH.py
PiicoDev_MPU6050.py
PiicoDev_MS5637.py
PiicoDev_Potentiometer.py
PiicoDev_QMC6310.py
PiicoDev_RFID.py
PiicoDev_RFID_Expansion.py
PiicoDev_RGB.py
PiicoDev_RV3028.py
PiicoDev_SSD1306.py
PiicoDev_Servo.py
PiicoDev_Switch.py
PiicoDev_TMP117.py
PiicoDev_Transceiver.py
PiicoDev_Ultrasonic.py
PiicoDev_Unified.py
PiicoDev_VEML6030.py
PiicoDev_VEML6040.py
PiicoDev_VL53L1X.py
piicodev-1.10.3.dist-info/LICENSE.md
piicodev-1.10.3.dist-info/METADATA
piicodev-1.10.3.dist-info/WHEEL
piicodev-1.10.3.dist-info/top_level.txt
piicodev-1.10.3.dist-info/RECORD
