Metadata-Version: 2.1
Name: piicodev
Version: 1.10.3
Summary: MicroPython Drivers for the PiicoDev ecosystem of sensors and modules
Home-page: https://github.com/CoreElectronics/CE-PiicoDev-PyPI
Author: Core Electronics
Author-email: production.inbox@coreelectronics.com.au
Classifier: Programming Language :: Python :: 3
Classifier: Programming Language :: Python :: 3.6
Classifier: Programming Language :: Python :: 3.7
Classifier: Programming Language :: Python :: Implementation :: MicroPython
Classifier: License :: OSI Approved :: MIT License
License-File: LICENSE.md
Requires-Dist: smbus2>=0.4.1
Provides-Extra: dev
Requires-Dist: pytest>=3.7; extra == "dev"
